LICENSE
MANIFEST.in
README.rst
setup.py
translations/.gitignore
translations/__init__.py
translations/__init__.pyc
translations/admin.py
translations/context_processors.py
translations/forms.py
translations/managers.py
translations/middleware.py
translations/models.py
translations/urls.py
translations/utils.py
translations/views.py
translations/templates/language_switcher.html
translations/templates/admin/edit_translation_messages.html
translations/templates/admin/translation_messages.html
translations/templates/admin/edit_inline/translatable-inline.html
translations/templates/admin/includes/fieldset-with-hidden-language.html
translations/templates/admin/includes/translation_messages_list.html
translations/templates/admin/translations/language/change_form.html
translations/templatetags/__init__.py
translations/templatetags/translations_tags.py
yawd_translations.egg-info/PKG-INFO
yawd_translations.egg-info/SOURCES.txt
yawd_translations.egg-info/dependency_links.txt
yawd_translations.egg-info/requires.txt
yawd_translations.egg-info/top_level.txt